configsys/__init__.py
configsys/config.py
configsys/example.py
configsys/utils.py
configsys-0.3.0.dist-info/LICENSE
configsys-0.3.0.dist-info/METADATA
configsys-0.3.0.dist-info/WHEEL
configsys-0.3.0.dist-info/RECORD
