Metadata-Version: 2.1
Name: configsys
Version: 0.3.0
Summary: 
License: MIT
Author: Erik Gafni
Author-email: egafni@gmail.com
Requires-Python: >=3.10,<4.0
Classifier: License :: OSI Approved :: MIT License
Classifier: Programming Language :: Python :: 3
Classifier: Programming Language :: Python :: 3.10
Classifier: Programming Language :: Python :: 3.11
Requires-Dist: dacite (>=1.8.1,<2.0.0)
Requires-Dist: fsspec (>=2023.10.0,<2024.0.0)
Requires-Dist: pyyaml (>=6.0.1,<7.0.0)
